elroy/__init__.py
elroy/defaults.yml
elroy/models.py
elroy/api/__init__.py
elroy/api/main.py
elroy/api/web.py
elroy/cli/bug_report.py
elroy/cli/chat.py
elroy/cli/main.py
elroy/cli/options.py
elroy/cli/slash_commands.py
elroy/cli/ui.py
elroy/cli/updater.py
elroy/config/__init__.py
elroy/config/env_vars.py
elroy/config/llm.py
elroy/config/paths.py
elroy/config/personas.py
elroy/core/__init__.py
elroy/core/async_tasks.py
elroy/core/configs.py
elroy/core/constants.py
elroy/core/ctx.py
elroy/core/latency.py
elroy/core/logging.py
elroy/core/session.py
elroy/core/tracing.py
elroy/db/__init__.py
elroy/db/db_manager.py
elroy/db/db_models.py
elroy/db/db_session.py
elroy/db/migrate.py
elroy/db/chroma/__init__.py
elroy/db/chroma/chroma_manager.py
elroy/db/chroma/chroma_session.py
elroy/db/chroma/migration.py
elroy/db/postgres/__init__.py
elroy/db/postgres/postgres_manager.py
elroy/db/postgres/postgres_session.py
elroy/db/postgres/alembic/__init__.py
elroy/db/postgres/alembic/alembic.ini
elroy/db/postgres/alembic/env.py
elroy/db/postgres/alembic/script.py.mako
elroy/db/postgres/alembic/versions/0fe803cc98f1_add_source_metadata_column.py
elroy/db/postgres/alembic/versions/1138d225c857_optional_goal_cols.py
elroy/db/postgres/alembic/versions/140daba72332_centralize_vectors.py
elroy/db/postgres/alembic/versions/18b5805a011b_unique_user_id.py
elroy/db/postgres/alembic/versions/1bf9bd811903_rename_archival_memory.py
elroy/db/postgres/alembic/versions/2c7579d11c8f_update_reminders.py
elroy/db/postgres/alembic/versions/33a33b6314d5_add_waitlist.py
elroy/db/postgres/alembic/versions/45223a2c0c67_init.py
elroy/db/postgres/alembic/versions/4ed800abf24a_rm_vector_timestamps.py
elroy/db/postgres/alembic/versions/5e1841a28c4b_add_messages_since_memory.py
elroy/db/postgres/alembic/versions/66a25cb7d3ef_add_assistant_name.py
elroy/db/postgres/alembic/versions/71ffabe55f21_add_system_instruct_to_user_preference.py
elroy/db/postgres/alembic/versions/7781f460cde2_add_memory_ops_table.py
elroy-0.3.0.dist-info/METADATA
elroy-0.3.0.dist-info/WHEEL
elroy-0.3.0.dist-info/entry_points.txt
elroy-0.3.0.dist-info/licenses/LICENSE
elroy-0.3.0.dist-info/RECORD
