Metadata-Version: 2.4
Name: elroy
Version: 0.3.0
Author-email: Elroy Bot <bot@elroy.ai>
License-File: LICENSE
Requires-Python: <3.13,>=3.10
Requires-Dist: alembic>=1.13.2
Requires-Dist: apscheduler>=3.11.0
Requires-Dist: chromadb>=0.4.22
Requires-Dist: click>=8.1.7
Requires-Dist: colorama>=0.4.6
Requires-Dist: docstring-parser>=0.16
Requires-Dist: fastapi>=0.104.0
Requires-Dist: importlib-resources
Requires-Dist: litellm>=1.75.5
Requires-Dist: lock>=2018.3.25.2110
Requires-Dist: pgvector>=0.3.6
Requires-Dist: prompt-toolkit>=3.0.47
Requires-Dist: psycopg2-binary>=2.9.9
Requires-Dist: pygments>=2.18.0
Requires-Dist: pytz>=2024.1
Requires-Dist: pyyaml>=6.0.1
Requires-Dist: requests>=2.32.2
Requires-Dist: rich>=13.7.1
Requires-Dist: scikit-learn>=1.6.0
Requires-Dist: semantic-version>=2.10.0
Requires-Dist: sqlalchemy>=2.0.29
Requires-Dist: sqlite-vec>=0.1.6
Requires-Dist: sqlmodel>=0.0.21
Requires-Dist: tiktoken>=0.8.0
Requires-Dist: toolz>=0.12.1
Requires-Dist: typer>=0.20.0
Requires-Dist: uvicorn>=0.24.0
Provides-Extra: dev
Requires-Dist: autoflake>=2.3.0; extra == 'dev'
Requires-Dist: black>=24.4.2; extra == 'dev'
Requires-Dist: bumpversion>=0.6.0; extra == 'dev'
Requires-Dist: discord-py; extra == 'dev'
Requires-Dist: fawltydeps>=0.15.0; extra == 'dev'
Requires-Dist: isort>=5.12.0; extra == 'dev'
Requires-Dist: langchain-core>=0.3.31; extra == 'dev'
Requires-Dist: lorem-text>=2.1; extra == 'dev'
Requires-Dist: pydantic>=2.10.3; extra == 'dev'
Requires-Dist: pylint>=3.3.1; extra == 'dev'
Requires-Dist: pyright>=1.1.350; extra == 'dev'
Requires-Dist: pytest-cov>=6.0.0; extra == 'dev'
Requires-Dist: pytest-mock>=3.14.0; extra == 'dev'
Requires-Dist: pytest-rerunfailures; extra == 'dev'
Requires-Dist: pytest>=8.1.1; extra == 'dev'
Requires-Dist: testcontainers>=3.7.1; extra == 'dev'
Requires-Dist: vulture>=2.11; extra == 'dev'
Provides-Extra: docs
Requires-Dist: mkdocs; extra == 'docs'
Requires-Dist: mkdocs-blog-plugin; extra == 'docs'
Requires-Dist: mkdocs-git-revision-date-localized-plugin; extra == 'docs'
Requires-Dist: mkdocs-macros-plugin; extra == 'docs'
Requires-Dist: mkdocs-material; extra == 'docs'
Requires-Dist: mkdocs-rss-plugin; extra == 'docs'
Provides-Extra: tracing
Requires-Dist: arize-phoenix; extra == 'tracing'
Requires-Dist: arize-phoenix-otel; extra == 'tracing'
Requires-Dist: openinference-instrumentation; extra == 'tracing'
Requires-Dist: openinference-instrumentation-litellm; extra == 'tracing'
Requires-Dist: openinference-semantic-conventions; extra == 'tracing'
